{
	"format_version": "1.12.0",
	"minecraft:geometry": [
		{
			"description": {
				"identifier": "geometry.unknown",
				"texture_width": 16,
				"texture_height": 16,
				"visible_bounds_width": 2,
				"visible_bounds_height": 1.5,
				"visible_bounds_offset": [0, 0.25, 0]
			},
			"bones": [
				{
					"name": "pageBone",
					"pivot": [2.75, 1.501, 0],
					"cubes": [
						{
							"origin": [-2.75, 1.5, -3.5],
							"size": [5.5, 0.001, 7],
							"uv": {
								"up": {"uv": [0, 0], "uv_size": [8, 10.25]},
								"down": {"uv": [8, 10.25], "uv_size": [8, -10.25]}
							}
						}
					]
				}
			]
		}
	]
}